{
  "30000340-null-null": {
    "name": "QUESTDESCRIPTION_30000340_NAME:[F]Develop",
    "desc": "QUESTDESCRIPTION_30000340_DESC:[F]Develop",
    "manual": "QUESTDESCRIPTION_30000340_MANUAL:[F]Develop",
    "complete": "QUESTDESCRIPTION_30000340_COMPLETE:[F]Develop",
    "count": "1",
    "locking": "0"
  },
  "30000340-Develop-": {
    "name": "QUESTDESCRIPTION_30000340_NAME:[F]Develop",
    "desc": "QUESTDESCRIPTION_30000340_DESC:[F]Develop",
    "manual": "QUESTDESCRIPTION_30000340_MANUAL:[F]Develop",
    "complete": "QUESTDESCRIPTION_30000340_COMPLETE:[F]Develop",
    "count": "1",
    "locking": "0"
  },
  "30000341-null-null": {
    "name": "QUESTDESCRIPTION_30000341_NAME:[F]Develop",
    "desc": "QUESTDESCRIPTION_30000341_DESC:[F]Develop",
    "manual": "QUESTDESCRIPTION_30000341_MANUAL:[F]Develop",
    "complete": "QUESTDESCRIPTION_30000341_COMPLETE:[F]Develop",
    "count": "1",
    "locking": "0"
  },
  "30000341-Develop-": {
    "name": "QUESTDESCRIPTION_30000341_NAME:[F]Develop",
    "desc": "QUESTDESCRIPTION_30000341_DESC:[F]Develop",
    "manual": "QUESTDESCRIPTION_30000341_MANUAL:[F]Develop",
    "complete": "QUESTDESCRIPTION_30000341_COMPLETE:[F]Develop",
    "count": "1",
    "locking": "0"
  }
}