{
  "150501010-null-null": {
    "name": "抽選で20名様に<FONT color='#FFD200'>キャラクタークッション</font>をプレゼントいたします。\n2日間ログインするとキャラクタークッションの抽選に応募できます。"
  },
  "150501040-null-null": {
    "name": "抽選で10名様に<FONT color='#FFD200'>最新型モニタ</font>をプレゼントいたします。\n5日間ログインすると最新型モニタの抽選に応募できます。"
  },
  "150501060-null-null": {
    "name": "抽選で10名様に<FONT color='#FFD200'>キャラクター商品セット</font>をプレゼントいたします。\n7日間ログインするとキャラクター商品セットの抽選に応募できます。"
  },
  "150501090-null-null": {
    "name": "抽選で1名様に<FONT color='#FFD200'>最新型パソコン</font>をプレゼントいたします。\n10日間ログインすると最新型パソコンの抽選に応募できます。"
  },
  "150526010-null-null": {
    "name": "抽選で20名様に<FONT color='#FFD200'>キャラクタークッション</font>をプレゼントいたします。\n2日間ログインするとキャラクタークッションの抽選に応募できます。"
  },
  "150526040-null-null": {
    "name": "抽選で10名様に<FONT color='#FFD200'>最新型モニタ</font>をプレゼントいたします。\n5日間ログインすると最新型モニタの抽選に応募できます。"
  },
  "150526060-null-null": {
    "name": "抽選で10名様に<FONT color='#FFD200'>キャラクター商品セット</font>をプレゼントいたします。\n7日間ログインするとキャラクター商品セットの抽選に応募できます。"
  },
  "150526090-null-null": {
    "name": "抽選で1名様に<FONT color='#FFD200'>最新型パソコン</font>をプレゼントいたします。\n10日間ログインすると最新型パソコンの抽選に応募できます。"
  },
  "150501001-null-null": {
    "name": "はじめまして！記念のプレゼントをお渡しします。"
  },
  "150501011-null-null": {
    "name": "キャラクタークッションの抽選に応募しました！"
  },
  "150501021-null-null": {
    "name": "3回目の出席完了！プレゼントをお送りします。"
  },
  "150501031-null-null": {
    "name": "4回目の出席完了！プレゼントをお送りします。"
  },
  "150501041-null-null": {
    "name": "最新型モニタの抽選に応募しました！"
  },
  "150501051-null-null": {
    "name": "6目の出席完了！プレゼントをお送りします。"
  },
  "150501061-null-null": {
    "name": "キャラクター商品セットの抽選に応募しました！"
  },
  "150501071-null-null": {
    "name": "8回目の出席完了！プレゼントをお送りします。"
  },
  "150501081-null-null": {
    "name": "9回目の出席完了！プレゼントをお送りします。"
  },
  "150501091-null-null": {
    "name": "最新型パソコンの抽選に応募しました！"
  },
  "150526001-null-null": {
    "name": "1日目の出席完了！"
  },
  "150526011-null-null": {
    "name": "2日目の出席完了！"
  },
  "150526021-null-null": {
    "name": "3日目の出席完了！"
  },
  "150526031-null-null": {
    "name": "4日目の出席完了！"
  },
  "150526041-null-null": {
    "name": "5日目の出席完了！"
  },
  "150526051-null-null": {
    "name": "6日目の出席完了！"
  },
  "150526061-null-null": {
    "name": "7日目の出席完了！"
  },
  "150526071-null-null": {
    "name": "8日目の出席完了！"
  },
  "150526081-null-null": {
    "name": "9日目の出席完了！"
  },
  "150526091-null-null": {
    "name": "10日目の出席完了！"
  },
  "150605001-null-null": {
    "name": "1日目の出席完了！"
  },
  "150605011-null-null": {
    "name": "2日目の出席完了！"
  },
  "150605021-null-null": {
    "name": "3日目の出席完了！"
  },
  "150605031-null-null": {
    "name": "4日目の出席完了！"
  },
  "150605041-null-null": {
    "name": "5日目の出席完了！"
  },
  "150605051-null-null": {
    "name": "6日目の出席完了！"
  },
  "150605061-null-null": {
    "name": "7日目の出席完了！"
  },
  "150605071-null-null": {
    "name": "8日目の出席完了！"
  },
  "150605081-null-null": {
    "name": "9日目の出席完了！"
  },
  "150605091-null-null": {
    "name": "10日目の出席完了！"
  },
  "150605101-null-null": {
    "name": "11日目の出席完了！"
  },
  "150605111-null-null": {
    "name": "12日目の出席完了！"
  },
  "150605121-null-null": {
    "name": "13日目の出席完了！"
  },
  "150605131-null-null": {
    "name": "14日目の出席完了！"
  },
  "150605141-null-null": {
    "name": "15日目の出席完了！"
  },
  "150605151-null-null": {
    "name": "16日目の出席完了！"
  },
  "150605161-null-null": {
    "name": "17日目の出席完了！"
  },
  "150605171-null-null": {
    "name": "18日目の出席完了！"
  },
  "150605181-null-null": {
    "name": "19日目の出席完了！"
  },
  "150605191-null-null": {
    "name": "20日目の出席完了！"
  },
  "150605201-null-null": {
    "name": "21日目の出席完了！"
  },
  "150628001-null-null": {
    "name": "1日目の出席完了！"
  },
  "150628011-null-null": {
    "name": "2日目の出席完了！"
  },
  "150628021-null-null": {
    "name": "3日目の出席完了！"
  },
  "150628031-null-null": {
    "name": "4日目の出席完了！"
  },
  "150628041-null-null": {
    "name": "5日目の出席完了！"
  },
  "150628051-null-null": {
    "name": "6日目の出席完了！"
  },
  "150628061-null-null": {
    "name": "7日目の出席完了！"
  },
  "150707001-null-null": {
    "name": "1日目の出席完了！メイプルストーリー2へようこそ！"
  },
  "150707011-null-null": {
    "name": "2日目の出席完了！今日も会えて嬉しいです！"
  },
  "150707021-null-null": {
    "name": "3日目の出席完了！プレゼントをお渡しします。"
  },
  "150707031-null-null": {
    "name": "4日目の出席完了！楽しい一日を！"
  },
  "150707041-null-null": {
    "name": "5日目の出席完了！また会えて嬉しいです！"
  },
  "150707051-null-null": {
    "name": "6日目の出席完了！プレゼントをお渡しします。"
  },
  "150707061-null-null": {
    "name": "7日目の出席完了！明日もまた来てくださいね！"
  },
  "150707071-null-null": {
    "name": "8日目の出席完了！今日のプレゼントは!?"
  },
  "150707081-null-null": {
    "name": "9日目の出席完了！今日も会えて嬉しいです！"
  },
  "150707091-null-null": {
    "name": "10日目の出席完了！プレゼントをお渡しします。"
  },
  "150707101-null-null": {
    "name": "11日目の出席完了！今日も元気でいきましょう！"
  },
  "150707111-null-null": {
    "name": "12日目の出席完了！今日も楽しく過ごしましょう！"
  },
  "150707121-null-null": {
    "name": "13日目の出席完了！ドキドキ！プレゼントをプレゼントいたします！"
  },
  "150707131-null-null": {
    "name": "14日目の出席完了！明日もお待ちしてます！"
  },
  "150707141-null-null": {
    "name": "15日目の出席完了！プレゼントをお渡しします。"
  },
  "150707151-null-null": {
    "name": "16日目の出席完了！また会えて嬉しいです！"
  },
  "150707161-null-null": {
    "name": "17日目の出席完了！ぜひご活用ください！"
  },
  "150707171-null-null": {
    "name": "18日目の出席完了！明日も来てくださいね！"
  },
  "150707181-null-null": {
    "name": "19日目の出席完了！今日のプレゼントは!?"
  },
  "150707191-null-null": {
    "name": "20日目の出席完了！明日、最後のプレゼントを忘れずに受け取ってくださいね！"
  },
  "150707201-null-null": {
    "name": "21日の出席、全て完了！次回のイベントをお楽しみに！"
  },
  "150728001-null-null": {
    "name": "1日目の出席完了！"
  },
  "150728011-null-null": {
    "name": "2日目の出席完了！"
  },
  "150728021-null-null": {
    "name": "3日目の出席完了！"
  },
  "150728031-null-null": {
    "name": "4日目の出席完了！"
  },
  "150728041-null-null": {
    "name": "5日目の出席完了！"
  },
  "150728051-null-null": {
    "name": "6日目の出席完了！"
  },
  "150728061-null-null": {
    "name": "7日目の出席完了！"
  },
  "150728071-null-null": {
    "name": "8日目の出席完了！"
  },
  "150728081-null-null": {
    "name": "9日目の出席完了！"
  },
  "150728091-null-null": {
    "name": "10日目の出席完了！"
  },
  "150728101-null-null": {
    "name": "11日目の出席完了！"
  },
  "150728111-null-null": {
    "name": "12日目の出席完了！"
  },
  "150728121-null-null": {
    "name": "13日目の出席完了！"
  },
  "150728131-null-null": {
    "name": "14日目の出席完了！"
  },
  "150728141-null-null": {
    "name": "15日目の出席完了！"
  },
  "150728151-null-null": {
    "name": "16日目の出席完了！"
  },
  "150728161-null-null": {
    "name": "17日目の出席完了！"
  },
  "150728171-null-null": {
    "name": "18日目の出席完了！"
  },
  "150728181-null-null": {
    "name": "19日目の出席完了！"
  },
  "150728191-null-null": {
    "name": "20日目の出席完了！"
  },
  "150728201-null-null": {
    "name": "21日目の出席完了！"
  },
  "150818001-null-null": {
    "name": "1日目の出席完了！"
  },
  "150818011-null-null": {
    "name": "2日目の出席完了！"
  },
  "150818021-null-null": {
    "name": "3日目の出席完了！"
  },
  "150818031-null-null": {
    "name": "4日目の出席完了！"
  },
  "150818041-null-null": {
    "name": "5日目の出席完了！"
  },
  "150818051-null-null": {
    "name": "6日目の出席完了！"
  },
  "150818061-null-null": {
    "name": "7日目の出席完了！"
  },
  "150818071-null-null": {
    "name": "8日目の出席完了！"
  },
  "150818081-null-null": {
    "name": "9日目の出席完了！"
  },
  "150818091-null-null": {
    "name": "10日目の出席完了！"
  },
  "150818101-null-null": {
    "name": "11日目の出席完了！"
  },
  "150818111-null-null": {
    "name": "12日目の出席完了！"
  },
  "150818121-null-null": {
    "name": "13日目の出席完了！"
  },
  "150818131-null-null": {
    "name": "14日目の出席完了！"
  },
  "150818141-null-null": {
    "name": "15日目の出席完了！"
  },
  "150818151-null-null": {
    "name": "16日目の出席完了！"
  },
  "150818161-null-null": {
    "name": "17日目の出席完了！"
  },
  "150818171-null-null": {
    "name": "18日目の出席完了！"
  },
  "150818181-null-null": {
    "name": "19日目の出席完了！"
  },
  "150818191-null-null": {
    "name": "20日目の出席完了！"
  },
  "150818201-null-null": {
    "name": "21日目の出席完了！"
  },
  "150731001-null-null": {
    "name": "1日目の出席完了！"
  },
  "150731011-null-null": {
    "name": "2日目の出席完了！"
  },
  "150731021-null-null": {
    "name": "3日目の出席完了！"
  },
  "150731031-null-null": {
    "name": "4日目の出席完了！"
  },
  "150731041-null-null": {
    "name": "5日目の出席完了！"
  },
  "150731051-null-null": {
    "name": "6日目の出席完了！"
  },
  "150731061-null-null": {
    "name": "7日目の出席完了！"
  },
  "150731071-null-null": {
    "name": "8日目の出席完了！"
  },
  "150731081-null-null": {
    "name": "9日目の出席完了！"
  },
  "150731091-null-null": {
    "name": "10日目の出席完了！"
  },
  "150731101-null-null": {
    "name": "11日目の出席完了！"
  },
  "150731111-null-null": {
    "name": "12日目の出席完了！"
  },
  "150731121-null-null": {
    "name": "13日目の出席完了！"
  },
  "150731131-null-null": {
    "name": "14日目の出席完了！"
  },
  "150707100-null-null": {
    "name": "抽選で200名様に<FONT color='#FFD200'>500ブルーメロット</font>をプレゼントいたします。\nログインするだけで抽選に応募できます。"
  },
  "150707120-null-null": {
    "name": "抽選で100名様に<FONT color='#FFD200'>1,000円分のNEXONポイント</font>をプレゼントいたします。\nログインするだけで抽選に応募できます。"
  },
  "150707150-null-null": {
    "name": "抽選で5名様に<FONT color='#FFD200'>自分だけのパソコン</font>をプレゼントいたします。\nログインするだけで抽選に応募できます。"
  },
  "150707190-null-null": {
    "name": "抽選で200名様に<FONT color='#FFD200'>1,000ブルーメロット</font>をプレゼントいたします。\nログインするだけで抽選に応募できます。"
  },
  "150731010-null-null": {
    "name": "抽選で5名様に<FONT color='#FFD200'>自分だけのパソコン</font>をプレゼントいたします。\nログインするだけで抽選に応募できます。"
  },
  "150820001-null-null": {
    "name": "1日目の出席完了！"
  },
  "150820011-null-null": {
    "name": "2日目の出席完了！"
  },
  "150820021-null-null": {
    "name": "3日目の出席完了！"
  },
  "150820031-null-null": {
    "name": "4日目の出席完了！"
  },
  "150820041-null-null": {
    "name": "5日目の出席完了！"
  },
  "150820051-null-null": {
    "name": "6日目の出席完了！"
  },
  "150820061-null-null": {
    "name": "7日目の出席完了！"
  },
  "150820071-null-null": {
    "name": "8日目の出席完了！"
  },
  "150820081-null-null": {
    "name": "9日目の出席完了！"
  },
  "150820091-null-null": {
    "name": "10日目の出席完了！"
  },
  "150820101-null-null": {
    "name": "11日目の出席完了！"
  },
  "150820111-null-null": {
    "name": "12日目の出席完了！"
  },
  "150820121-null-null": {
    "name": "13日目の出席完了！"
  },
  "150820131-null-null": {
    "name": "14日目の出席完了！"
  },
  "150820030-null-null": {
    "name": "抽選で100名様に<FONT color='#FFD200'>500円分のNEXONポイント</font>をプレゼントいたします。\nログインするだけで抽選に応募できます。"
  },
  "150820060-null-null": {
    "name": "抽選で100名様に<FONT color='#FFD200'>500ブルーメロット</font>をプレゼントいたします。\nログインするだけで抽選に応募できます。"
  },
  "150820080-null-null": {
    "name": "抽選で100名様に<FONT color='#FFD200'>1,000円分のNEXONポイント</font>をプレゼントいたします。\nログインするだけで抽選に応募できます。"
  },
  "150820110-null-null": {
    "name": "抽選で100名様に<FONT color='#FFD200'>1,000ブルーメロット</font>をプレゼントいたします。\nログインするだけで抽選に応募できます。"
  },
  "150922001-null-null": {
    "name": "1日目の出席完了！"
  },
  "150922011-null-null": {
    "name": "2日目の出席完了！"
  },
  "150922021-null-null": {
    "name": "3日目の出席完了！"
  },
  "150922031-null-null": {
    "name": "4日目の出席完了！"
  },
  "150922041-null-null": {
    "name": "5日目の出席完了！"
  },
  "150922051-null-null": {
    "name": "6日目の出席完了！"
  },
  "150922061-null-null": {
    "name": "7日目の出席完了！"
  },
  "150922071-null-null": {
    "name": "8日目の出席完了！"
  },
  "150922081-null-null": {
    "name": "9日目の出席完了！"
  },
  "150922091-null-null": {
    "name": "10日目の出席完了！"
  },
  "150922101-null-null": {
    "name": "11日目の出席完了！"
  },
  "150922111-null-null": {
    "name": "12日目の出席完了！"
  },
  "150922121-null-null": {
    "name": "13日目の出席完了！"
  },
  "150922131-null-null": {
    "name": "14日目の出席完了！"
  },
  "150922020-null-null": {
    "name": "抽選で5名様に<FONT color='#FFD200'>500円分のNEXONポイント</font>をプレゼントいたします。\nログインするだけで抽選に応募できます。"
  },
  "150922040-null-null": {
    "name": "抽選で5名様に<FONT color='#FFD200'>サムスンのヘッドセット</font>をプレゼントいたします。\nログインするだけで抽選に応募できます。"
  },
  "150922060-null-null": {
    "name": "抽選で5名様に<FONT color='#FFD200'>500円分のNEXONポイント</font>をプレゼントいたします。\nログインするだけで抽選に応募できます。"
  },
  "150922090-null-null": {
    "name": "抽選で5名様に<FONT color='#FFD200'>500円分のNEXONポイント</font>をプレゼントいたします。\nログインするだけで抽選に応募できます。"
  },
  "150922110-null-null": {
    "name": "抽選で5名様に<FONT color='#FFD200'>サムスンのヘッドセット</font>をプレゼントいたします。\nログインするだけで抽選に応募できます。"
  },
  "150922130-null-null": {
    "name": "抽選で5名様に<FONT color='#FFD200'>500円分のNEXONポイント</font>をプレゼントいたします。\nログインするだけで抽選に応募できます。"
  },
  "151015001-null-null": {
    "name": "1日目の出席完了！"
  },
  "151015011-null-null": {
    "name": "2日目の出席完了！"
  },
  "151015021-null-null": {
    "name": "3日目の出席完了！"
  },
  "151015031-null-null": {
    "name": "4日目の出席完了！"
  },
  "151015041-null-null": {
    "name": "5日目の出席完了！"
  },
  "151015051-null-null": {
    "name": "6日目の出席完了！"
  },
  "151015061-null-null": {
    "name": "7日目の出席完了！"
  },
  "151015071-null-null": {
    "name": "8日目の出席完了！"
  },
  "151015081-null-null": {
    "name": "9日目の出席完了！"
  },
  "151015091-null-null": {
    "name": "10日目の出席完了！"
  },
  "151015101-null-null": {
    "name": "11日目の出席完了！"
  },
  "151015111-null-null": {
    "name": "12日目の出席完了！"
  },
  "151015121-null-null": {
    "name": "13日目の出席完了！"
  },
  "151015131-null-null": {
    "name": "14日目の出席完了！"
  },
  "151015141-null-null": {
    "name": "15日目の出席完了！"
  },
  "151231001-null-null": {
    "name": "1日目の出席完了！"
  },
  "151231011-null-null": {
    "name": "2日目の出席完了！"
  },
  "151231021-null-null": {
    "name": "3日目の出席完了！"
  },
  "151231031-null-null": {
    "name": "4日目の出席完了！"
  },
  "151231041-null-null": {
    "name": "5日目の出席完了！"
  },
  "151231051-null-null": {
    "name": "6日目の出席完了！"
  },
  "151231061-null-null": {
    "name": "7日目の出席完了！"
  },
  "151231071-null-null": {
    "name": "8日目の出席完了！"
  },
  "151231081-null-null": {
    "name": "9日目の出席完了！"
  },
  "151231091-null-null": {
    "name": "10日目の出席完了！"
  },
  "151231101-null-null": {
    "name": "11日目の出席完了！"
  },
  "151231111-null-null": {
    "name": "12日目の出席完了！"
  },
  "151231121-null-null": {
    "name": "13日目の出席完了！"
  },
  "151231131-null-null": {
    "name": "14日目の出席完了！"
  },
  "151126001-null-null": {
    "name": "1日目の出席完了！"
  },
  "151126011-null-null": {
    "name": "2日目の出席完了！"
  },
  "151126021-null-null": {
    "name": "3日目の出席完了！"
  },
  "151126031-null-null": {
    "name": "4日目の出席完了！"
  },
  "151126041-null-null": {
    "name": "5日目の出席完了！"
  },
  "151126051-null-null": {
    "name": "6日目の出席完了！"
  },
  "151126061-null-null": {
    "name": "7日目の出席完了！"
  },
  "151126071-null-null": {
    "name": "8日目の出席完了！"
  },
  "151126081-null-null": {
    "name": "9日目の出席完了！"
  },
  "151126091-null-null": {
    "name": "10日目の出席完了！"
  },
  "151126101-null-null": {
    "name": "11日目の出席完了！"
  },
  "151126111-null-null": {
    "name": "12日目の出席完了！"
  },
  "151126121-null-null": {
    "name": "13日目の出席完了！"
  },
  "151126131-null-null": {
    "name": "14日目の出席完了！"
  },
  "160526001-null-null": {
    "name": "1日目の出席完了！"
  },
  "160526011-null-null": {
    "name": "2日目の出席完了！"
  },
  "160526021-null-null": {
    "name": "3日目の出席完了！"
  },
  "160526031-null-null": {
    "name": "4日目の出席完了！"
  },
  "160526041-null-null": {
    "name": "5日目の出席完了！"
  },
  "160526051-null-null": {
    "name": "6日目の出席完了！"
  },
  "160526061-null-null": {
    "name": "7日目の出席完了！"
  },
  "160526071-null-null": {
    "name": "8日目の出席完了！"
  },
  "160526081-null-null": {
    "name": "9日目の出席完了！"
  },
  "160526091-null-null": {
    "name": "10日目の出席完了！"
  },
  "160526101-null-null": {
    "name": "11日目の出席完了！"
  },
  "160526111-null-null": {
    "name": "12日目の出席完了！"
  },
  "160526121-null-null": {
    "name": "13日目の出席完了！"
  },
  "160526131-null-null": {
    "name": "14日目の出席完了！"
  }
}