{
  "10200001-null-null": {
    "name": "レイジスラッシュ"
  },
  "10200002-null-null": {
    "name": "レイジスラッシュ2打"
  },
  "10200002-Develop-null": {
    "name": "レイジスラッシュ2打"
  },
  "10200003-null-null": {
    "name": "レイジスラッシュ3打"
  },
  "10200003-Develop-null": {
    "name": "レイジスラッシュ3打"
  },
  "10200004-null-null": {
    "name": "レイジスラッシュ4打"
  },
  "10200004-Develop-null": {
    "name": "レイジスラッシュ4打"
  },
  "10200005-null-null": {
    "name": "レイジスラッシュ5打"
  },
  "10200005-Develop-null": {
    "name": "レイジスラッシュ5打"
  },
  "10200011-null-null": {
    "name": "スウィープ"
  },
  "10200012-null-null": {
    "name": "スウィープ2打"
  },
  "10200012-Develop-null": {
    "name": "スウィープ2打"
  },
  "10200013-null-null": {
    "name": "スウィープ3打"
  },
  "10200013-Develop-null": {
    "name": "スウィープ3打"
  },
  "10200014-null-null": {
    "name": "スウィープ4打"
  },
  "10200014-Develop-null": {
    "name": "スウィープ4打"
  },
  "10200015-null-null": {
    "name": "スウィープ5打"
  },
  "10200015-Develop-null": {
    "name": "スウィープ5打"
  },
  "10200021-null-null": {
    "name": "戦士の一撃"
  },
  "10200031-null-null": {
    "name": "闇のオーラ"
  },
  "10200041-null-null": {
    "name": "ボイドスラッシュ"
  },
  "10200042-null-null": {
    "name": "ボイドスラッシュ2打"
  },
  "10200042-Develop-null": {
    "name": "ボイドスラッシュ2打"
  },
  "10200051-null-null": {
    "name": "血の渇望"
  },
  "10200061-null-null": {
    "name": "威嚇"
  },
  "10200062-null-null": {
    "name": "威嚇強化型"
  },
  "10200063-null-null": {
    "name": "威嚇スタン効果"
  },
  "10200071-null-null": {
    "name": "グラウンドクラッシュ"
  },
  "10200072-null-null": {
    "name": "グラウンドクラッシュスプラッシュ"
  },
  "10200072-Develop-null": {
    "name": "グラウンドクラッシュスプラッシュ"
  },
  "10200081-null-null": {
    "name": "アドレナリン"
  },
  "10200082-null-null": {
    "name": "アドレナリン2段階"
  },
  "10200083-null-null": {
    "name": "アドレナリン3段階"
  },
  "10200091-null-null": {
    "name": "エックススラッシュ"
  },
  "10200101-null-null": {
    "name": "エンデュア"
  },
  "10200111-null-null": {
    "name": "出血"
  },
  "10200112-null-null": {
    "name": "出血発動"
  },
  "10200112-Develop-null": {
    "name": "出血発動"
  },
  "10200121-null-null": {
    "name": "ラージソードマスタリ"
  },
  "10200131-null-null": {
    "name": "ダークコマンダー"
  },
  "10200141-null-null": {
    "name": "血の祭物"
  },
  "10200151-null-null": {
    "name": "闘争心"
  },
  "10200161-null-null": {
    "name": "地震"
  },
  "10200162-null-null": {
    "name": "地震スプラッシュ"
  },
  "10200162-Develop-null": {
    "name": "地震スプラッシュ"
  },
  "10200171-null-null": {
    "name": "エアリアルスマッシュ"
  },
  "10200171-JobChange_01-null": {
    "name": "エアリアルスマッシュ"
  },
  "10200172-null-null": {
    "name": "エアリアルスマッシュ2打"
  },
  "10200172-Develop-null": {
    "name": "エアリアルスマッシュ2打"
  },
  "10200181-null-null": {
    "name": "パリーザムーン"
  },
  "10200181-JobChange_01-null": {
    "name": "パリーザムーン"
  },
  "10200182-null-null": {
    "name": "パリーザムーン2打"
  },
  "10200182-Develop-null": {
    "name": "パリーザムーン2打"
  },
  "10200183-null-null": {
    "name": "パリーザムーンスプラッシュ"
  },
  "10200183-Develop-null": {
    "name": "パリーザムーンスプラッシュ"
  },
  "10200184-null-null": {
    "name": "パリーザムーンスプラッシュ2"
  },
  "10200184-Develop-null": {
    "name": "パリーザムーンスプラッシュ2"
  },
  "10200191-null-null": {
    "name": "無限の闇"
  },
  "10200191-JobChange_01-null": {
    "name": "無限の闇"
  },
  "10200201-null-null": {
    "name": "スカルスプリッター"
  },
  "10200201-JobChange_01-null": {
    "name": "スカルスプリッター"
  },
  "10200202-null-null": {
    "name": "スカルスプリッター2段階"
  },
  "10200202-Develop-null": {
    "name": "スカルスプリッター2段階"
  },
  "10200203-null-null": {
    "name": "スカルスプリッター3段階"
  },
  "10200203-Develop-null": {
    "name": "スカルスプリッター3段階"
  },
  "10200204-null-null": {
    "name": "スカルスプリッター3段階"
  },
  "10200204-Develop-null": {
    "name": "スカルスプリッター3段階"
  },
  "10200205-null-null": {
    "name": "スカルスプリッター3段階チャージ攻撃"
  },
  "10200205-Develop-null": {
    "name": "スカルスプリッター3段階チャージ攻撃"
  },
  "10200206-null-null": {
    "name": "スカルスプリッター3段階チャージ攻撃"
  },
  "10200206-Develop-null": {
    "name": "スカルスプリッター3段階チャージ攻撃"
  },
  "10200207-null-null": {
    "name": "戦士の一撃"
  },
  "10200207-JobChange_01-null": {
    "name": "戦士の一撃"
  },
  "10200211-null-null": {
    "name": "血の狂乱"
  },
  "10200211-JobChange_01-null": {
    "name": "血の狂乱"
  },
  "10200221-null-null": {
    "name": "狂戦士の魂"
  },
  "10200221-JobChange_01-null": {
    "name": "狂戦士の魂"
  },
  "10200231-null-null": {
    "name": "突風"
  },
  "10200231-JobChange_01-null": {
    "name": "突風"
  },
  "10200232-null-null": {
    "name": "突風2打"
  },
  "10200232-Develop-null": {
    "name": "突風2打"
  },
  "10200233-null-null": {
    "name": "つむじ風"
  },
  "10200233-JobChange_01-null": {
    "name": "つむじ風"
  },
  "10200234-null-null": {
    "name": "つむじ風"
  },
  "10200234-JobChange_01-null": {
    "name": "つむじ風"
  },
  "10200241-null-null": {
    "name": "傷口破壊"
  },
  "10200241-JobChange_01-null": {
    "name": "傷口破壊"
  },
  "10200251-null-null": {
    "name": "ブラッドスラッシュ"
  },
  "10200251-JobChange_01-null": {
    "name": "ブラッドスラッシュ"
  },
  "10200252-null-null": {
    "name": "ブラッドスラッシュ2打"
  },
  "10200252-Develop-null": {
    "name": "ブラッドスラッシュ2打"
  },
  "10200253-null-null": {
    "name": "ブラッドスラッシュ3打"
  },
  "10200253-Develop-null": {
    "name": "ブラッドスラッシュ3打"
  },
  "10200254-null-null": {
    "name": "ブラッドスラッシュパッシブ"
  },
  "10200254-Develop-null": {
    "name": "ブラッドスラッシュパッシブ"
  },
  "10200255-null-null": {
    "name": "ダークブラッドスラッシュ"
  },
  "10200255-JobChange_01-null": {
    "name": "ダークブラッドスラッシュ"
  },
  "10200256-null-null": {
    "name": "ダークブラッドスラッシュ2打"
  },
  "10200256-Develop-null": {
    "name": "ダークブラッドスラッシュ2打"
  },
  "10200257-null-null": {
    "name": "ブラッドスラッシュ回転攻撃"
  },
  "10200257-JobChange_01-null": {
    "name": "ブラッドスラッシュ回転攻撃"
  },
  "10200261-null-null": {
    "name": "SKILLNAME_10200261_NAME:[F]JobChange_02"
  },
  "10200261-JobChange_02-null": {
    "name": "SKILLNAME_10200261_NAME:[F]JobChange_02"
  },
  "10200271-null-null": {
    "name": "SKILLNAME_10200271_NAME:[F]JobChange_02"
  },
  "10200271-JobChange_02-null": {
    "name": "SKILLNAME_10200271_NAME:[F]JobChange_02"
  },
  "10200281-null-null": {
    "name": "SKILLNAME_10200281_NAME:[F]JobChange_02"
  },
  "10200281-JobChange_02-null": {
    "name": "SKILLNAME_10200281_NAME:[F]JobChange_02"
  },
  "10200291-null-null": {
    "name": "SKILLNAME_10200291_NAME:[F]JobChange_02"
  },
  "10200291-JobChange_02-null": {
    "name": "SKILLNAME_10200291_NAME:[F]JobChange_02"
  }
}