<?xml version="1.0" encoding="utf-8"?>
<npcAi>
	<reserved>
		<condition name="hpLess" value="110">
			<node name="SetValue" key="phase" value="1" />
			<node name="standby" limit="2500" faceTarget="0" />
		</condition>
	</reserved>
	<battle>
		<node name="conditions">
			<condition name="extraData" key="phase" value="1">
				<node name="skill" idx="1" />
				<node name="SetValue" key="phase" value="2" />
			</condition>
			<condition name="true">
				<node name="standby" limit="3000" faceTarget="1" />
			</condition>
		</node>
	</battle>
</npcAi>