{
  "70200001--": {
    "locking": "0",
    "count": "1",
    "name": "Participa en el evento de MC Kay"
  },
  "70200002--": {
    "count": "1",
    "locking": "1",
    "name": "Obtén una bonificación de mazmorra aleatoria"
  },
  "70200003--": {
    "count": "1",
    "locking": "1",
    "name": "Derrota a los enemigos en el $map:02000176$"
  },
  "70200004--": {
    "locking": "1",
    "name": "Derrota a los enemigos en el $map:02000261$",
    "count": "1"
  },
  "70200005--": {
    "count": "1",
    "locking": "1",
    "name": "Derrota a los enemigos en el $map:02000260$"
  },
  "70200006--": {
    "count": "1",
    "locking": "1",
    "name": "Derrota a los enemigos en el $map:02000263$"
  },
  "70200007--": {
    "count": "1",
    "locking": "1",
    "name": "Derrota a los enemigos en el $map:02000264$"
  },
  "70200008--": {
    "name": "Derrota a los enemigos en el $map:02000411$",
    "count": "1",
    "locking": "1"
  },
  "70200009--": {
    "count": "1",
    "locking": "1",
    "name": "Derrota a los enemigos en el $map:02000412$"
  },
  "70200010--": {
    "count": "1",
    "locking": "1",
    "name": "Derrota a los enemigos en el $map:02000413$"
  },
  "70200011--": {
    "count": "1",
    "locking": "1",
    "name": "Derrota a los enemigos en el $map:02000414$"
  },
  "70200012--": {
    "count": "1",
    "locking": "1",
    "name": "Derrota a los enemigos en el $map:02000415$"
  },
  "70200013--": {
    "locking": "1",
    "name": "Derrota a los enemigos en el $map:02000235$",
    "count": "1"
  },
  "70200014--": {
    "count": "1",
    "locking": "1",
    "name": "Derrota a los enemigos en el $map:02000236$"
  },
  "70200015--": {
    "count": "1",
    "locking": "1",
    "name": "Derrota a los enemigos en el $map:02000416$"
  },
  "70200016--": {
    "count": "1",
    "locking": "1",
    "name": "Derrota a los enemigos en el $map:02010014$"
  },
  "70200017--": {
    "count": "1",
    "locking": "1",
    "name": "Derrota a $npc:21000559$ o $npc:21000554$ en $map:02000416$"
  },
  "70200018--": {
    "count": "1",
    "locking": "1",
    "name": "Derrota a $npc:21000556$ o $npc:21000551$ en $map:02000417$"
  },
  "70200019--": {
    "count": "1",
    "locking": "1",
    "name": "Mata a $npc:21000552$ o $npc:21000548$ en $map:02000235$"
  },
  "70200020--": {
    "count": "1",
    "locking": "1",
    "name": "Derrota a $npc:21000554$ o $npc:21000550$ en $map:02000235$"
  },
  "70200021--": {
    "count": "1",
    "locking": "1",
    "name": "Mata a $npc:21091042$ o $npc:21091046$ en $map:02000415$"
  }
}
