{
  "1--": {
    "name": "Beds"
  },
  "2--": {
    "name": "Tables"
  },
  "3--": {
    "name": "Sofas & Chairs"
  },
  "4--": {
    "name": "Storage"
  },
  "5--": {
    "name": "Wall Decorations"
  },
  "6--": {
    "name": "Wall Tiles"
  },
  "7--": {
    "name": "Bathroom"
  },
  "8--": {
    "name": "Lighting"
  },
  "9--": {
    "name": "Electronics"
  },
  "10--": {
    "name": "Fences"
  },
  "11--": {
    "name": "Nature Terrain"
  },
  "12--": {
    "name": "Garden"
  },
  "13--": {
    "name": "Special Blocks"
  },
  "14--": {
    "name": "Stairs"
  },
  "15--": {
    "name": "Doors"
  },
  "16--": {
    "name": "Common Terrain"
  },
  "17--": {
    "name": "Vegetation"
  },
  "18--": {
    "name": "Interior Decor"
  },
  "19--": {
    "name": "Themed Decor"
  },
  "20--": {
    "name": "Structures"
  },
  "21--": {
    "name": "Trap"
  },
  "91--": {
    "name": "Assistant"
  },
  "92--": {
    "name": "Souvenirs"
  },
  "93--": {
    "name": "Templates"
  },
  "94--": {
    "name": "Event"
  },
  "95--": {
    "name": "Red Star Shop"
  },
  "96--": {
    "name": "Blue Star Shop"
  },
  "97--": {
    "name": "Dungeon Helper"
  },
  "99--": {
    "name": "Unused"
  },
  "101--": {
    "name": "Furnishings"
  },
  "102--": {
    "name": "Special"
  },
  "103-Mastery-": {
    "name": "Life Skill Items"
  },
  "104--": {
    "name": ""
  },
  "105--": {
    "name": "Designs"
  },
  "106--": {
    "name": "Assistants"
  },
  "107--": {
    "name": "Development"
  },
  "108--": {
    "name": "Recent"
  },
  "201--": {
    "name": "All"
  },
  "203--": {
    "name": "NEW"
  },
  "204-Mastery-": {
    "name": "Ranching Supplies"
  },
  "205-MasterySecond-": {
    "name": "Farming Supplies"
  },
  "501--": {
    "name": "Highest Price"
  },
  "502--": {
    "name": "Lowest Price"
  },
  "503--": {
    "name": "Name, Ascending"
  },
  "504--": {
    "name": "Name, Descending"
  },
  "505--": {
    "name": "Sort By"
  },
  "506--": {
    "name": "Recent"
  },
  "601--": {
    "name": "Purpose"
  },
  "602--": {
    "name": "Theme"
  },
  "603--": {
    "name": "Color"
  },
  "1001--": {
    "name": "Tria"
  },
  "1002--": {
    "name": "Henesys"
  },
  "1003--": {
    "name": "Ellinia"
  },
  "1004--": {
    "name": "Kerning City"
  },
  "1005--": {
    "name": "Perion"
  },
  "1006--": {
    "name": "Taliskar"
  },
  "1007--": {
    "name": "Lith Harbor"
  },
  "1008--": {
    "name": "Karkar"
  },
  "1009--": {
    "name": "Calibre"
  },
  "1010--": {
    "name": "Alikar"
  },
  "10000--": {
    "name": "Misc"
  },
  "20000--": {
    "name": "Bamboo Bathroom"
  },
  "20001--": {
    "name": "September's New Products"
  },
  "20002--": {
    "name": "((China Only)) Ray Prop Exhibition"
  },
  "80000--": {
    "name": "Rainbow Slime"
  },
  "80001--": {
    "name": "Pumpkin Devils"
  },
  "80002-Event-": {
    "name": "Wampus"
  },
  "90000--": {
    "name": "Limited Time (until 10/11)"
  },
  "90001--": {
    "name": "#Limited Sale (until 9/4)"
  },
  "99998--": {
    "name": "NEW"
  },
  "99999--": {
    "name": "HOT"
  }
}