<?xml version="1.0" encoding="utf-8"?>
<npcAi>
	<!--전투-->
	<battle>
		<node name="select" prob="999999,9999,9999,0">
			<node name="standby" limit="500" faceTarget="0" cooltime="999999">
				<node name="SetValue" key="IsGrab" value="0" />
				<node name="standby" limit="12000" faceTarget="1" />
			</node>
			<node name="standby" limit="10" faceTarget="1" cooltime="6000" initialCooltime="1">
				<node name="select" prob="100,100">
					<node name="target" type="rand" from="10" to="1200" />
					<node name="standby" limit="1000" faceTarget="1" />
				</node>
			</node>
			<node name="standby" limit="10" faceTarget="1" cooltime="5000" initialCooltime="1">
				<node name="target" type="far" from="10" to="1200" />
				<node name="trace" till="300" limit="5000" />
			</node>
			<node name="conditions">
				<condition name="hpOver" value="80">
					<node name="select" prob="999999,99999,0">
						<node name="standby" limit="500" faceTarget="0" cooltime="999999" initialCooltime="2000">
							<node name="SetValueRangeTarget" key="FireFire" value="1" radius="9000" />
							<node name="trace" till="300" limit="5000" />
						</node>
						<node name="standby" limit="500" faceTarget="0" cooltime="50000" initialCooltime="25000">
							<node name="SetValueRangeTarget" key="MaskOrder" value="1" radius="9000" />
							<node name="standby" limit="2000" faceTarget="1" />
							<node name="target" type="rand" from="10" to="1200" />
							<node name="standby" limit="500" faceTarget="1" />
							<node name="skill" idx="1" />
							<node name="target" type="rand" from="10" to="1200" />
							<node name="standby" limit="500" faceTarget="1" />
							<node name="skill" idx="1" />
							<node name="target" type="rand" from="10" to="1200" />
							<node name="standby" limit="500" faceTarget="1" />
							<node name="skill" idx="1" />
							<node name="standby" limit="2000" faceTarget="1" />
							<node name="SetValueRangeTarget" key="MaskOrder" value="3" radius="9000" />
							<node name="standby" limit="2000" faceTarget="1" />
						</node>
						<node name="conditions">
							<condition name="skillRange" skillIdx="1">
								<node name="select" prob="9999,9999,100,100">
									<node name="standby" limit="10" faceTarget="1" cooltime="45000" initialCooltime="1">
										<node name="select" prob="100,100">
											<node name="move" destination="-1250,950,2400" animation="Run_A" speed="600">
												<node name="target" type="rand" from="10" to="1200" />
												<node name="skill" idx="3" />
												<node name="target" type="rand" from="10" to="1200" />
												<node name="skill" idx="1" />
												<node name="target" type="rand" from="10" to="1200" />
												<node name="skill" idx="5" />
												<node name="standby" limit="2000" faceTarget="1" />
											</node>
											<node name="move" destination="75,825,2400" animation="Run_A" speed="600">
												<node name="target" type="rand" from="10" to="1200" />
												<node name="skill" idx="5" />
												<node name="target" type="rand" from="10" to="1200" />
												<node name="skill" idx="3" />
												<node name="target" type="far" from="10" to="2000" />
												<node name="skill" idx="2" />
												<node name="standby" limit="2000" faceTarget="1" />
											</node>
										</node>
									</node>
									<node name="standby" limit="10" faceTarget="1" cooltime="15000" initialCooltime="20000">
										<node name="select" prob="100,100">
											<node name="skill" idx="5" />
											<node name="standby" limit="2000" faceTarget="1" />
										</node>
									</node>
									<node name="skill" cooltime="7000" idx="1">
										<node name="standby" limit="2000" faceTarget="1" />
									</node>
									<node name="skill" cooltime="20000" idx="1">
										<node name="target" type="far" from="10" to="2000" />
										<node name="skill" idx="2" />
										<node name="standby" limit="2000" faceTarget="1" />
									</node>
								</node>
							</condition>
							<condition name="true">
								<node name="select" prob="100,100">
									<node name="trace" limit="2500" skillIdx="1" />
									<node name="standby" limit="1000" faceTarget="1" />
								</node>
							</condition>
						</node>
					</node>
				</condition>
				<condition name="hpOver" value="40">
					<node name="select" prob="999999,99999,9999,9999,0">
						<node name="standby" limit="500" faceTarget="0" cooltime="999999" initialCooltime="2000">
							<node name="SetValueRangeTarget" key="FireFire" value="1" radius="9000" />
							<node name="trace" till="300" limit="5000" />
						</node>
						<node name="standby" limit="500" faceTarget="0" cooltime="50000" initialCooltime="1">
							<node name="select" prob="100,100">
								<node name="SetValueRangeTarget" key="MaskOrder" value="1" radius="9000">
									<node name="summon" npcId="1" npcCount="3" npcCountMax="3" group="101" summonPos="-700,900,2400" summonRadius="400, 400, 0" />
									<node name="standby" limit="3000" faceTarget="1" />
									<node name="target" type="far" from="10" to="2000" />
									<node name="skill" idx="2" />
									<node name="standby" limit="1000" faceTarget="1" />
									<node name="skill" idx="4" />
									<node name="standby" limit="2000" faceTarget="1" />
									<node name="SetValueRangeTarget" key="MaskOrder" value="3" radius="9000" />
									<node name="standby" limit="1500" faceTarget="1" />
								</node>
								<node name="SetValueRangeTarget" key="MaskOrder" value="1" radius="9000">
									<node name="summon" npcId="1" npcCount="3" npcCountMax="3" group="101" summonPos="-700,900,2400" summonRadius="400, 400, 0" />
									<node name="standby" limit="3000" faceTarget="1" />
									<node name="target" type="far" from="10" to="2000" />
									<node name="skill" idx="2" />
									<node name="standby" limit="1000" faceTarget="1" />
									<node name="skill" idx="4" />
									<node name="standby" limit="2000" faceTarget="1" />
									<node name="SetValueRangeTarget" key="MaskOrder" value="3" radius="9000" />
									<node name="standby" limit="1500" faceTarget="1" />
								</node>
							</node>
						</node>
						<node name="standby" limit="10" faceTarget="1" cooltime="15000" initialCooltime="1">
							<node name="skill" idx="5" />
						</node>
						<node name="standby" limit="10" faceTarget="1" cooltime="20000" initialCooltime="1">
							<node name="select" prob="40,40,40">
								<node name="move" destination="-1350,1800,2400">
									<node name="skill" faceTarget="0" idx="6" />
									<node name="skill" faceTarget="0" idx="7" />
									<node name="skill" faceTarget="0" idx="7" />
									<node name="skill" faceTarget="0" idx="7" />
									<node name="skill" faceTarget="0" idx="8" />
									<node name="standby" limit="2000" faceTarget="1" />
								</node>
								<node name="move" destination="-600,900,2400">
									<node name="skill" faceTarget="0" idx="6" />
									<node name="skill" faceTarget="0" idx="7" />
									<node name="skill" faceTarget="0" idx="7" />
									<node name="skill" faceTarget="0" idx="7" />
									<node name="skill" faceTarget="0" idx="8" />
									<node name="standby" limit="2000" faceTarget="1" />
								</node>
								<node name="move" destination="150,300,2400">
									<node name="skill" faceTarget="0" idx="6" />
									<node name="skill" faceTarget="0" idx="7" />
									<node name="skill" faceTarget="0" idx="7" />
									<node name="skill" faceTarget="0" idx="7" />
									<node name="skill" faceTarget="0" idx="8" />
									<node name="standby" limit="2000" faceTarget="1" />
								</node>
							</node>
						</node>
						<node name="conditions">
							<condition name="skillRange" skillIdx="1">
								<node name="select" prob="100,100,100">
									<node name="skill" cooltime="7000" idx="1">
										<node name="standby" limit="2000" faceTarget="1" />
									</node>
									<node name="skill" cooltime="20000" idx="1">
										<node name="target" type="far" from="10" to="2000" />
										<node name="skill" idx="2" />
										<node name="standby" limit="2000" faceTarget="1" />
									</node>
									<node name="skill" cooltime="7000" idx="3">
										<node name="standby" limit="3000" faceTarget="1" />
									</node>
								</node>
							</condition>
							<condition name="true">
								<node name="select" prob="100,100">
									<node name="trace" limit="2500" skillIdx="1" />
									<node name="standby" limit="1000" faceTarget="1" />
								</node>
							</condition>
						</node>
					</node>
				</condition>
				<condition name="true">
					<node name="select" prob="999999,999999,99999,99999,0">
						<node name="standby" limit="500" faceTarget="0" cooltime="90000" initialCooltime="2000">
							<node name="SetValueRangeTarget" key="FireFire" value="1" radius="9000" />
							<node name="trace" till="300" limit="5000" />
						</node>
						<node name="standby" limit="500" faceTarget="0" cooltime="999999">
							<node name="move" destination="-600,900,2400" animation="Attack_01_G" speed="1200" />
							<node name="target" type="rand" from="10" to="1200" />
							<node name="skill" idx="12" />
							<node name="standby" limit="1000" faceTarget="1" />
						</node>
						<node name="standby" limit="500" faceTarget="0" cooltime="50000" initialCooltime="1">
							<node name="summon" npcId="1" npcCount="3" npcCountMax="3" group="101" summonPos="-700,900,2400" summonRadius="400, 400, 0" />
							<node name="summon" npcId="1" npcCount="3" npcCountMax="3" group="101" summonPos="-700,900,2400" summonRadius="400, 400, 0" />
							<node name="standby" limit="1000" faceTarget="1" />
							<node name="target" type="far" from="10" to="2000" />
							<node name="skill" idx="2" />
							<node name="standby" limit="1000" faceTarget="1" />
							<node name="skill" idx="11" />
							<node name="standby" limit="1000" faceTarget="1" />
						</node>
						<node name="standby" limit="500" faceTarget="0" cooltime="80000">
							<node name="SetValueRangeTarget" key="MaskOrder" value="2" radius="9000">
								<node name="target" type="rand" from="10" to="1200" />
								<node name="standby" limit="3000" faceTarget="1" />
								<node name="skill" idx="4" />
								<node name="target" type="rand" from="10" to="1200" />
								<node name="skill" idx="9" />
								<node name="standby" limit="1000" faceTarget="1" />
								<node name="SetValueRangeTarget" key="MaskOrder" value="3" radius="9000" />
								<node name="standby" limit="1000" faceTarget="1" />
								<node name="skill" idx="12" />
							</node>
						</node>
						<node name="conditions">
							<condition name="extraData" key="IsGrab" value="1">
								<node name="move" destination="-600,900,2400" animation="Attack_01_G" speed="1200">
									<node name="SetValue" key="IsGrab" value="0" />
									<node name="skill" facePos="-1350, 300, 2400" idx="12" />
								</node>
							</condition>
							<condition name="extraData" key="IsGrab" value="2">
								<node name="move" destination="-600,900,2400" animation="Attack_01_G" speed="1200">
									<node name="SetValue" key="IsGrab" value="0" />
									<node name="skill" facePos="-1350, 1800, 2400" idx="12" />
								</node>
							</condition>
							<condition name="extraData" key="IsGrab" value="3">
								<node name="move" destination="-600,900,2400" animation="Attack_01_G" speed="1200">
									<node name="SetValue" key="IsGrab" value="0" />
									<node name="skill" facePos="150, 300, 2400" idx="12" />
								</node>
							</condition>
							<condition name="true">
								<node name="select" prob="9999,9999,9999,0">
									<node name="standby" limit="10" faceTarget="1" cooltime="15000" initialCooltime="1">
										<node name="skill" idx="5" />
									</node>
									<node name="standby" limit="10" faceTarget="1" cooltime="15000" initialCooltime="1">
										<node name="skill" idx="11" />
									</node>
									<node name="standby" limit="10" faceTarget="1" cooltime="15000" initialCooltime="1">
										<node name="select" prob="100,100,100">
											<node name="skill" idx="9">
												<node name="target" type="far" from="10" to="2000" />
												<node name="standby" limit="1000" faceTarget="1" />
												<node name="skill" idx="9" />
												<node name="target" type="far" from="10" to="2000" />
												<node name="standby" limit="3000" faceTarget="1" />
											</node>
											<node name="skill" idx="9">
												<node name="target" type="far" from="10" to="2000" />
												<node name="standby" limit="1000" faceTarget="1" />
												<node name="skill" idx="10" />
												<node name="target" type="far" from="10" to="2000" />
												<node name="skill" idx="9" />
												<node name="standby" limit="3000" faceTarget="1" />
											</node>
											<node name="skill" idx="10">
												<node name="target" type="far" from="10" to="2000" />
												<node name="standby" limit="1000" faceTarget="1" />
												<node name="skill" idx="9" />
												<node name="target" type="far" from="10" to="2000" />
												<node name="standby" limit="3000" faceTarget="1" />
											</node>
										</node>
									</node>
									<node name="conditions">
										<condition name="skillRange" skillIdx="1">
											<node name="select" prob="100,100,100,100">
												<node name="skill" cooltime="7000" idx="1">
													<node name="standby" limit="1500" faceTarget="1" />
												</node>
												<node name="skill" cooltime="20000" idx="2">
													<node name="target" type="far" from="10" to="2000" />
													<node name="skill" idx="10" />
													<node name="standby" limit="1500" faceTarget="1" />
												</node>
												<node name="skill" cooltime="7000" idx="3">
													<node name="skill" idx="9" />
													<node name="standby" limit="1500" faceTarget="1" />
												</node>
												<node name="skill" cooltime="7000" idx="4">
													<node name="skill" idx="12" />
													<node name="standby" limit="1500" faceTarget="1" />
												</node>
											</node>
										</condition>
										<condition name="true">
											<node name="select" prob="100,100">
												<node name="trace" limit="2500" skillIdx="1" />
												<node name="standby" limit="1000" faceTarget="1" />
											</node>
										</condition>
									</node>
								</node>
							</condition>
						</node>
					</node>
				</condition>
			</node>
		</node>
	</battle>
	<battleEnd onlyDead="true">
		<node name="SetValueRangeTarget" key="MaskOrder" value="3" radius="9000" />
	</battleEnd>
</npcAi>